flake8_no_implicit_concat/__init__.py
flake8_no_implicit_concat/_version.py
flake8_no_implicit_concat-0.3.7.dist-info/LICENSE
flake8_no_implicit_concat-0.3.7.dist-info/METADATA
flake8_no_implicit_concat-0.3.7.dist-info/WHEEL
flake8_no_implicit_concat-0.3.7.dist-info/entry_points.txt
flake8_no_implicit_concat-0.3.7.dist-info/top_level.txt
flake8_no_implicit_concat-0.3.7.dist-info/RECORD
