Metadata-Version: 2.1
Name: flake8-no-implicit-concat
Version: 0.3.7
Summary: Flake8 plugin that forbids implicit str/bytes literal concatenations
Home-page: https://github.com/10sr/flake8-no-implicit-concat
Author: 10sr
Author-email: 8.slashes@gmail.com
License: MIT
Project-URL: Bug Tracker, https://github.com/10sr/flake8-no-implicit-concat/issues
Project-URL: Changelog, https://github.com/10sr/flake8-no-implicit-concat/blob/master/CHANGELOG.md
Keywords: flake8
Classifier: License :: OSI Approved :: MIT License
Classifier: Environment :: Console
Classifier: Framework :: Flake8
Classifier: Intended Audience :: Developers
Classifier: License :: OSI Approved :: MIT License
Classifier: Operating System :: OS Independent
Classifier: Programming Language :: Python :: 3
Classifier: Programming Language :: Python :: 3 :: Only
Classifier: Programming Language :: Python :: 3.6
Classifier: Programming Language :: Python :: 3.7
Classifier: Programming Language :: Python :: 3.8
Classifier: Programming Language :: Python :: 3.9
Classifier: Programming Language :: Python :: 3.10
Classifier: Programming Language :: Python :: 3.11
Classifier: Programming Language :: Python :: 3.12
Classifier: Programming Language :: Python :: 3.13
Classifier: Programming Language :: Python :: Implementation :: CPython
Classifier: Programming Language :: Python :: Implementation :: PyPy
Classifier: Topic :: Software Development :: Libraries :: Python Modules
Classifier: Topic :: Software Development :: Quality Assurance
Requires-Python: >=3.6
License-File: LICENSE
Requires-Dist: flake8
Requires-Dist: more-itertools; python_version < "3.10"
Provides-Extra: dev
Requires-Dist: black; extra == "dev"
Requires-Dist: isort; extra == "dev"
Requires-Dist: flake8; extra == "dev"
Requires-Dist: hacking>=4; extra == "dev"
Requires-Dist: flake8-black; extra == "dev"
Requires-Dist: flake8-isort; extra == "dev"
Requires-Dist: pep8-naming; extra == "dev"
Requires-Dist: flake8-broken-line; extra == "dev"
Requires-Dist: flake8-builtins; extra == "dev"
Requires-Dist: flake8-2020; extra == "dev"
Requires-Dist: flake8-docstrings; extra == "dev"
Requires-Dist: flake8-rst-docstrings; extra == "dev"
Requires-Dist: darglint; extra == "dev"
Requires-Dist: mypy; extra == "dev"
Requires-Dist: coverage; extra == "dev"
Requires-Dist: codecov; extra == "dev"
